gd/rpc/__init__.py
gd/rpc/__main__.py
gd/rpc/config.py
gd/rpc/main.py
gd/rpc/py.typed
gd/rpc/rpc.toml
gd_rpc-1.0.2.dist-info/entry_points.txt
gd_rpc-1.0.2.dist-info/LICENSE
gd_rpc-1.0.2.dist-info/METADATA
gd_rpc-1.0.2.dist-info/WHEEL
gd_rpc-1.0.2.dist-info/RECORD
