Metadata-Version: 2.1
Name: gd-rpc
Version: 1.0.2
Summary: Geometry Dash Discord Rich Presence.
Home-page: https://github.com/nekitdev/gd.rpc
License: MIT
Keywords: python,gd,presence
Author: nekitdev
Requires-Python: >=3.7
Classifier: Development Status :: 4 - Beta
Classifier: Intended Audience :: Developers
Classifier: License :: OSI Approved :: MIT License
Classifier: Operating System :: OS Independent
Classifier: Programming Language :: Python :: 3
Classifier: Programming Language :: Python :: 3.7
Classifier: Programming Language :: Python :: 3.8
Classifier: Programming Language :: Python :: 3.9
Classifier: Programming Language :: Python :: 3.10
Classifier: Programming Language :: Python :: 3.11
Classifier: Typing :: Typed
Requires-Dist: attrs (>=23.1.0)
Requires-Dist: entrypoint (>=1.4.0)
Requires-Dist: gd.py (>=1.0.0)
Requires-Dist: pypresence (>=4.2.1)
Requires-Dist: toml (>=0.10.2)
Requires-Dist: wraps (>=0.6.1)
Project-URL: Documentation, https://nekitdev.github.io/gd.rpc
Project-URL: Discord, https://nekit.dev/discord
Project-URL: Funding, https://patreon.com/nekitdev
Project-URL: Issues, https://github.com/nekitdev/gd.rpc/issues
Project-URL: Repository, https://github.com/nekitdev/gd.rpc
